{
	"schemaVersion": "4",
	"info": {
		"name": "versionLookup - get /version/check"
	},
	"parameter": {
		"properties": {
			"params": {
				"type": "object",
				"description": "The parameters from the endpoint."
			},
			"request": {
				"type": "object",
				"description": "The HTTP request."
			},
			"config": {
				"type": "object",
				"description": "The service's configuration"
			},
			"env": {
				"type": "object",
				"description": "The host OS environment"
			}
		},
		"additionalProperties": false,
		"required": [
			"request",
			"config",
			"env",
			"params"
		]
	},
	"start": "condition.1",
	"nodes": {
		"condition.1": {
			"type": "nodehandler://axway-flow/condition",
			"name": "Check filebeat version",
			"method": "equals",
			"parameters": [
				{
					"name": "value",
					"type": "jsonpath",
					"value": "$.config.versions.filebeat",
					"metaName": "Value",
					"metaDescription": "The value to test input against."
				},
				{
					"name": "source",
					"type": "jsonpath",
					"value": "$.params.filebeatVersion",
					"metaName": "Source",
					"metaDescription": "The input to test."
				}
			],
			"outputs": {
				"true": {
					"routes": [
						"condition.2"
					],
					"context": "$.equals",
					"metaName": "True"
				},
				"false": {
					"routes": [
						"http.1"
					],
					"context": "$.equals",
					"metaName": "False"
				}
			},
			"metaMethod": "Equals"
		},
		"http.1": {
			"type": "nodehandler://axway-flow/http",
			"name": "Filebeat version incorrect",
			"method": "setresponse",
			"parameters": [
				{
					"name": "status",
					"type": "number",
					"value": "500",
					"metaName": "Status",
					"metaDescription": "The HTTP status code"
				},
				{
					"name": "body",
					"type": "object",
					"value": "{\"message\":\"Filebeat version does not match to API-Builder release\", \"versionStatus\":\"error\"}",
					"metaName": "Body",
					"metaDescription": "The response payload"
				}
			],
			"outputs": {
				"next": {
					"context": "$.response",
					"routes": [],
					"metaName": "Next"
				}
			},
			"metaMethod": "Set HTTP Response"
		},
		"condition.2": {
			"type": "nodehandler://axway-flow/condition",
			"name": "Check logstash version",
			"method": "equals",
			"parameters": [
				{
					"name": "source",
					"type": "jsonpath",
					"value": "$.params.logstashVersion",
					"metaName": "Source",
					"metaDescription": "The input to test."
				},
				{
					"name": "value",
					"type": "jsonpath",
					"value": "$.config.versions.logstash",
					"metaName": "Value",
					"metaDescription": "The value to test input against."
				}
			],
			"outputs": {
				"true": {
					"routes": [
						"http.3"
					],
					"context": "$.equals",
					"metaName": "True"
				},
				"false": {
					"routes": [
						"http.2"
					],
					"context": "$.equals",
					"metaName": "False"
				}
			},
			"metaMethod": "Equals"
		},
		"http.2": {
			"type": "nodehandler://axway-flow/http",
			"name": "Logstash version incorrect",
			"method": "setresponse",
			"parameters": [
				{
					"name": "status",
					"type": "number",
					"value": "500",
					"metaName": "Status",
					"metaDescription": "The HTTP status code"
				},
				{
					"name": "body",
					"type": "object",
					"value": "{\"message\":\"Logstash version does not match to API-Builder release\", \"versionStatus\":\"error\"}",
					"metaName": "Body",
					"metaDescription": "The response payload"
				}
			],
			"outputs": {
				"next": {
					"context": "$.response",
					"routes": [],
					"metaName": "Next"
				}
			},
			"metaMethod": "Set HTTP Response"
		},
		"http.3": {
			"type": "nodehandler://axway-flow/http",
			"name": "Set HTTP Response",
			"method": "setresponse",
			"parameters": [
				{
					"name": "status",
					"type": "number",
					"value": "200",
					"metaName": "Status",
					"metaDescription": "The HTTP status code"
				},
				{
					"name": "body",
					"type": "object",
					"value": "{\"message\":\"Filebeat and Logstash version okay\", \"versionStatus\":\"ok\"}",
					"metaName": "Body",
					"metaDescription": "The response payload"
				}
			],
			"outputs": {
				"next": {
					"context": "$.response",
					"routes": [],
					"metaName": "Next"
				}
			},
			"metaMethod": "Set HTTP Response"
		}
	}
}